qaviton_package_manager/__init__.py
qaviton_package_manager/__main__.py
qaviton_package_manager/cli.py
qaviton_package_manager/conf.py
qaviton_package_manager/exceptions.py
qaviton_package_manager/manager.py
qaviton_package_manager/manager_methods/__init__.py
qaviton_package_manager/manager_methods/clean_requirements.py
qaviton_package_manager/manager_methods/create_manager.py
qaviton_package_manager/manager_methods/distribute_to_git.py
qaviton_package_manager/manager_methods/distribute_to_pypi.py
qaviton_package_manager/manager_methods/install_requirements.py
qaviton_package_manager/manager_methods/remove_requirements.py
qaviton_package_manager/manager_methods/test_package.py
qaviton_package_manager/manager_methods/update_requirements.py
qaviton_package_manager/utils/__init__.py
qaviton_package_manager/utils/cache_cred.py
qaviton_package_manager/utils/cryp.py
qaviton_package_manager/utils/functions.py
qaviton_package_manager/utils/logger.py
qaviton_package_manager/utils/package_manager.py
qaviton_package_manager/utils/settings.py
qaviton_package_manager/utils/shortcuts.py
qaviton_package_manager-2019.10.22.14.18.9.619355.dist-info/LICENSE
qaviton_package_manager-2019.10.22.14.18.9.619355.dist-info/METADATA
qaviton_package_manager-2019.10.22.14.18.9.619355.dist-info/WHEEL
qaviton_package_manager-2019.10.22.14.18.9.619355.dist-info/entry_points.txt
qaviton_package_manager-2019.10.22.14.18.9.619355.dist-info/top_level.txt
qaviton_package_manager-2019.10.22.14.18.9.619355.dist-info/RECORD
