Metadata-Version: 2.1
Name: qaviton-package-manager
Version: 2019.10.22.14.18.9.619355
Summary: a package manager for git projects with private repositories
Home-page: https://github.com/qaviton/qaviton_package_manager
Author: Qaviton
Author-email: info@qaviton.com
License: apache-2.0
Platform: UNKNOWN
Classifier: Programming Language :: Python :: 3.6
Classifier: Operating System :: OS Independent
Requires-Python: !=2.*,!=3.0.*,!=3.1.*,!=3.2.*,!=3.3.*,!=3.4.*,!=3.5.*
Requires-Dist: packaging (>=19.1)
Requires-Dist: pip (>=10.0.1)
Requires-Dist: requests (>=2.22.0)
Requires-Dist: psutil (>=5.6.3)
Requires-Dist: cryptography (>=2.7)
Requires-Dist: setuptools (>=38.6.0)
Requires-Dist: qaviton-helpers (>=2019.9.22.19.9.22.537577)
Requires-Dist: qaviton-handlers (>=2019.9.29.7.56.30.312631)
Requires-Dist: qaviton-processes (>=2019.10.16.3.27.36.160569)
Requires-Dist: qaviton-pip (>=2019.9.23.3.13.21.799826)
Requires-Dist: qaviton-git (>=2019.9.29.11.11.3.489379)
